genlic.py
genlic-0.1.0.dist-info/LICENSE
genlic-0.1.0.dist-info/METADATA
genlic-0.1.0.dist-info/WHEEL
genlic-0.1.0.dist-info/entry_points.txt
genlic-0.1.0.dist-info/top_level.txt
genlic-0.1.0.dist-info/RECORD
