Metadata-Version: 2.1
Name: genlic
Version: 0.1.0
Summary: A script for generating LICENSE files
Author-email: Samuel Eisenhandler <sgeisenhandler@gmail.com>
Classifier: Programming Language :: Python :: 3
Classifier: License :: OSI Approved :: MIT License
Classifier: Operating System :: OS Independent
Requires-Python: >=3.10
License-File: LICENSE
Requires-Dist: marshmallow
